SpringSaLaDpy/DrawingTool.py
SpringSaLaDpy/MolDraw_exec.py
SpringSaLaDpy/Project_reader.py
SpringSaLaDpy/Reader_functions.py
SpringSaLaDpy/__init__.py
SpringSaLaDpy/data_locator.py
SpringSaLaDpy/digit_counter.py
SpringSaLaDpy/display_info.py
SpringSaLaDpy/editor.py
SpringSaLaDpy/executable.py
SpringSaLaDpy/format_directory.py
SpringSaLaDpy/input_file_extraction.py
SpringSaLaDpy/langevin-ubuntu-latest
SpringSaLaDpy/langevin-windows-latest.exe
SpringSaLaDpy/langevin_x64
SpringSaLaDpy/test.py
SpringSaLaDpy/time_rounder.py
SpringSaLaDpy/MolDraw/DrawingTool.py
SpringSaLaDpy/MolDraw/MolDraw_exec.py
SpringSaLaDpy/MolDraw/__init__.py
SpringSaLaDpy/Visualization/Average_z_pos.py
SpringSaLaDpy/Visualization/Bound_fraction.py
SpringSaLaDpy/Visualization/ClusTopology_ss.py
SpringSaLaDpy/Visualization/ClusterCrossLinking.py
SpringSaLaDpy/Visualization/Cluster_comp.py
SpringSaLaDpy/Visualization/Composition.py
SpringSaLaDpy/Visualization/Composition_calculator.py
SpringSaLaDpy/Visualization/Counter.py
SpringSaLaDpy/Visualization/DataPy.py
SpringSaLaDpy/Visualization/Format.py
SpringSaLaDpy/Visualization/Histogram.py
SpringSaLaDpy/Visualization/Molclustpy_visualization_funcitons.py
SpringSaLaDpy/Visualization/MoleculeCounter.py
SpringSaLaDpy/Visualization/Plotter.py
SpringSaLaDpy/Visualization/Spatial_Analysis.py
SpringSaLaDpy/Visualization/__init__.py
SpringSaLaDpy/Visualization/acs_histogram.py
SpringSaLaDpy/Visualization/clustering.py
SpringSaLaDpy/Visualization/cs_independent.py
SpringSaLaDpy/Visualization/ssalad_ClusterAnalysis.py
SpringSaLaDpy/Visualization/times_2_title.py
springsaladpy-0.1.11.dist-info/METADATA
springsaladpy-0.1.11.dist-info/WHEEL
springsaladpy-0.1.11.dist-info/licenses/LICENSE
springsaladpy-0.1.11.dist-info/RECORD
